{
  "project_info": {
    "project_number": "1027141217245",
    "firebase_url": "https://tanksensr-default-rtdb.asia-southeast1.firebasedatabase.app",
    "project_id": "tanksensr",
    "storage_bucket": "tanksensr.firebasestorage.app"
  },
  "client": [
    {
      "client_info": {
        "mobilesdk_app_id": "1:1027141217245:android:fd5f71dd5e572744222434",
        "android_client_info": {
          "package_name": "com.app.firebaseiotapp"
        }
      },
      "oauth_client": [],
      "api_key": [
        {
          "current_key": "AIzaSyDUYwAgwoaj83CXnXcnTc-iwedMx0JJGZ4"
        }
      ],
      "services": {
        "appinvite_service": {
          "other_platform_oauth_client": []
        }
      }
    }
  ],
  "configuration_version": "1"
}